otteroad/__init__.py
otteroad/avro/__init__.py
otteroad/avro/model.py
otteroad/avro/serializer.py
otteroad/consumer/__init__.py
otteroad/consumer/handlers/__init__.py
otteroad/consumer/handlers/base.py
otteroad/consumer/handlers/registry.py
otteroad/consumer/service.py
otteroad/consumer/worker.py
otteroad/models/__init__.py
otteroad/models/avro/graph_events/public/RegionMatrixUpdated.avsc
otteroad/models/avro/graph_events/scenarios/RegionalScenarioMatrixUpdated.avsc
otteroad/models/avro/indicator_events/public/IndicatorValuesUpdated.avsc
otteroad/models/avro/indicator_events/scenarios/RegionalScenarioIndicatorsUpdated.avsc
otteroad/models/avro/indicator_events/scenarios/ScenarioIndicatorsUpdated.avsc
otteroad/models/avro/scenario_events/projects/BaseScenarioCreated.avsc
otteroad/models/avro/scenario_events/projects/ProjectCreated.avsc
otteroad/models/avro/scenario_events/projects/ScenarioObjectsUpdated.avsc
otteroad/models/avro/scenario_events/projects/ScenarioZonesUpdated.avsc
otteroad/models/avro/scenario_events/regional_scenarios/RegionalScenarioCreated.avsc
otteroad/models/avro/urban_events/functional_zones/FunctionalZonesUpdated.avsc
otteroad/models/avro/urban_events/soc_groups/SocGroupsUpdated.avsc
otteroad/models/avro/urban_events/territories/TerritoriesDeleted.avsc
otteroad/models/avro/urban_events/territories/TerritoriesUpdated.avsc
otteroad/models/avro/urban_events/urban_objects/UrbanObjectsUpdated.avsc
otteroad/models/graph_events/__init__.py
otteroad/models/graph_events/public/RegionMatrixUpdated.py
otteroad/models/graph_events/scenarios/RegionalScenarioMatrixUpdated.py
otteroad/models/indicator_events/__init__.py
otteroad/models/indicator_events/public/IndicatorValuesUpdated.py
otteroad/models/indicator_events/scenarios/RegionalScenarioIndicatorsUpdated.py
otteroad/models/indicator_events/scenarios/ScenarioIndicatorsUpdated.py
otteroad/models/scenario_events/__init__.py
otteroad/models/scenario_events/projects/BaseScenarioCreated.py
otteroad-0.2.2.dist-info/LICENSE
otteroad-0.2.2.dist-info/METADATA
otteroad-0.2.2.dist-info/WHEEL
otteroad-0.2.2.dist-info/RECORD
